tagent/CLAUDE.md
tagent/GEMINI.md
tagent/__init__.py
tagent/__main__.py
tagent/agent.py
tagent/cli.py
tagent/config.py
tagent/instructions_rag.py
tagent/llm_interface.py
tagent/llm_providers.py
tagent/memory_manager.py
tagent/model_config.py
tagent/models.py
tagent/prompt_builder.py
tagent/semantic_search.py
tagent/state_machine.py
tagent/task_actions.py
tagent/task_agent.py
tagent/token_utils.py
tagent/tool_executor.py
tagent/tool_rag.py
tagent/utils.py
tagent/version.py
tagent/ui/__init__.py
tagent/ui/factory.py
tagent/ui/institutional.py
tagent/ui/interface.py
tagent/ui/modern_cli.py
tagent-0.6.4.dist-info/licenses/LICENSE
tagent-0.6.4.dist-info/METADATA
tagent-0.6.4.dist-info/WHEEL
tagent-0.6.4.dist-info/entry_points.txt
tagent-0.6.4.dist-info/top_level.txt
tagent-0.6.4.dist-info/RECORD
