Metadata-Version: 2.4
Name: tagent
Version: 0.6.4
Summary: TAgent - Modular AI Agent Framework with Dynamic Tool Discovery
Author-email: TAgent Development Team <tagent@example.com>
Maintainer-email: TAgent Development Team <tagent@example.com>
License-Expression: MIT
Project-URL: Homepage, https://github.com/yourusername/tagent2
Project-URL: Documentation, https://github.com/yourusername/tagent2
Project-URL: Repository, https://github.com/yourusername/tagent2.git
Project-URL: Bug Tracker, https://github.com/yourusername/tagent2/issues
Keywords: ai,agent,llm,automation,framework
Classifier: Development Status :: 3 - Alpha
Classifier: Intended Audience :: Developers
Classifier: Programming Language :: Python :: 3
Classifier: Programming Language :: Python :: 3.8
Classifier: Programming Language :: Python :: 3.9
Classifier: Programming Language :: Python :: 3.10
Classifier: Programming Language :: Python :: 3.11
Classifier: Programming Language :: Python :: 3.12
Classifier: Topic :: Software Development :: Libraries :: Python Modules
Classifier: Topic :: Scientific/Engineering :: Artificial Intelligence
Requires-Python: >=3.8
License-File: LICENSE
Requires-Dist: pydantic>=2.0.0
Requires-Dist: litellm>=1.0.0
Requires-Dist: rich>=13.0.0
Requires-Dist: typing_extensions>=4.0.0
Requires-Dist: python-dotenv>=1.0.0
Requires-Dist: scikit-learn>=1.0.0
Requires-Dist: numpy>=1.20.0
Provides-Extra: dev
Requires-Dist: black>=23.0.0; extra == "dev"
Requires-Dist: flake8>=6.0.0; extra == "dev"
Requires-Dist: pytest>=7.0.0; extra == "dev"
Requires-Dist: pytest-cov>=4.0.0; extra == "dev"
Requires-Dist: mypy>=1.0.0; extra == "dev"
Requires-Dist: isort>=5.0.0; extra == "dev"
Requires-Dist: build>=0.8.0; extra == "dev"
Requires-Dist: twine>=4.0.0; extra == "dev"
Dynamic: license-file
